{
    "name": "Steve Double", 
    "facebook_url": "https://www.facebook.com/stevedouble2015", 
    "full_url": "https://www.conservatives.com/OurTeam/Prospective_Parliamentary_Candidates/Double_Stephen.aspx", 
    "phone": "01726 86902", 
    "email": "office@stevedouble.org.uk", 
    "address": "Kingsley Village\nPenhale\nFraddon\nSt Columb\nTR9 6NA", 
    "path": "/OurTeam/Prospective_Parliamentary_Candidates/Double_Stephen.aspx", 
    "constituency": "St Austell and Newquay", 
    "homepage": "stevedouble.org.uk", 
    "slug": "Double_Stephen"
}