{
    "constituency": "Wolverhampton South East", 
    "email": "wse@suriaphotay.com", 
    "facebook_url": "https://www.facebook.com/suriaformp", 
    "full_url": "https://www.conservatives.com/OurTeam/Prospective_Parliamentary_Candidates/Photay_Suriya.aspx", 
    "homepage": "http://www.suriaphotay.com", 
    "image_url": "https://www.conservatives.com/~/media/Images/Site Redesign/Profile Pictures/Non target candidates/2212/Suria Photay.ashx", 
    "name": "Suria Photay", 
    "path": "/OurTeam/Prospective_Parliamentary_Candidates/Photay_Suriya.aspx", 
    "slug": "Photay_Suriya"
}