{
    "address": "Gloucester Liberal Democrats\nThe Bisley Room\nSpread Eagle Court\nNorthgate Street\nGloucester\nGL1 1SL", 
    "constituency": "Gloucester", 
    "email": "jeremy4glos@hotmail.com", 
    "facebook_url": "facebook.com/jeremy4glos", 
    "full_url": "http://www.libdems.org.uk/jeremy_hilton", 
    "homepage": "www.jeremyhilton.co.uk", 
    "image_url": "https://d3n8a8pro7vhmx.cloudfront.net/libdems/pages/7007/attachments/original/1417449046/key_Jeremy_Hilton.jpg?1417449046", 
    "name": "Jeremy Hilton", 
    "region": "South West", 
    "twitter_username": "jeremy4glos"
}