{
    "fielding_in": [], 
    "other_officers": [], 
    "campaigns_officer": "Mr Jason Budd", 
    "registered_date": "2013-03-26T00:00:00", 
    "descriptions": [], 
    "party_leader": "Mr Stephen Perry", 
    "nominating_officer": "Mr Jason Budd", 
    "emblems": [
        {
            "image": "raw_data/PP2038/Emblem_818.jpg", 
            "id": "818", 
            "description": "Emblem 1"
        }
    ], 
    "party_address": "20 Southernhay Avenue\r\nBristol\r\nAvon\r\nBS8 4TJ\r\nUnited Kingdom\r\n", 
    "email": "", 
    "gibraltar_party": false, 
    "financial_year_end": "31/12", 
    "status": "Authorised", 
    "fax": "", 
    "phone_extension": "", 
    "phone": "", 
    "treasurer": "Mr Stephen Perry", 
    "party_id": "PP2038", 
    "accounting_units": {
        "exempt_from_parliamentary_election_returns": false, 
        "exempt_from_quarterly_transaction_returns": true, 
        "exempt_from_quarterly_donation_returns": true
    }, 
    "register": "Great Britain", 
    "party_name": "Independents for Bristol", 
    "alternative_names": [
        ""
    ]
}